chuk_mcp/__init__.py
chuk_mcp/__main__.py
chuk_mcp/config.py
chuk_mcp/client/__init__.py
chuk_mcp/client/client.py
chuk_mcp/client/connection.py
chuk_mcp/mcp_client/__init__.py
chuk_mcp/mcp_client/host/__init__.py
chuk_mcp/mcp_client/host/environment.py
chuk_mcp/mcp_client/host/server_manager.py
chuk_mcp/protocol/__init__.py
chuk_mcp/protocol/fast_json.py
chuk_mcp/protocol/mcp_pydantic_base.py
chuk_mcp/protocol/features/__init__.py
chuk_mcp/protocol/features/batching.py
chuk_mcp/protocol/messages/__init__.py
chuk_mcp/protocol/messages/json_rpc_message.py
chuk_mcp/protocol/messages/message_method.py
chuk_mcp/protocol/messages/notifications.py
chuk_mcp/protocol/messages/send_message.py
chuk_mcp/protocol/messages/completions/__init__.py
chuk_mcp/protocol/messages/completions/send_messages.py
chuk_mcp/protocol/messages/initialize/__init__.py
chuk_mcp/protocol/messages/initialize/send_messages.py
chuk_mcp/protocol/messages/logging/__init__.py
chuk_mcp/protocol/messages/logging/send_messages.py
chuk_mcp/protocol/messages/ping/__init__.py
chuk_mcp/protocol/messages/ping/send_messages.py
chuk_mcp/protocol/messages/prompts/__init__.py
chuk_mcp/protocol/messages/prompts/notifications.py
chuk_mcp/protocol/messages/prompts/prompt.py
chuk_mcp/protocol/messages/prompts/send_messages.py
chuk_mcp/protocol/messages/resources/__init__.py
chuk_mcp/protocol/messages/resources/notifications.py
chuk_mcp/protocol/messages/resources/resource.py
chuk_mcp/protocol/messages/resources/resource_content.py
chuk_mcp/protocol/messages/resources/resource_template.py
chuk_mcp/protocol/messages/resources/send_messages.py
chuk_mcp/protocol/messages/roots/__init__.py
chuk_mcp/protocol/messages/roots/send_messages.py
chuk_mcp/protocol/messages/sampling/__init__.py
chuk_mcp/protocol/messages/sampling/send_messages.py
chuk_mcp/protocol/messages/tools/__init__.py
chuk_mcp/protocol/messages/tools/notifications.py
chuk_mcp/protocol/messages/tools/send_messages.py
chuk_mcp/protocol/messages/tools/tool.py
chuk_mcp-0.9.1.dist-info/licenses/LICENSE
chuk_mcp-0.9.1.dist-info/METADATA
chuk_mcp-0.9.1.dist-info/WHEEL
chuk_mcp-0.9.1.dist-info/entry_points.txt
chuk_mcp-0.9.1.dist-info/top_level.txt
chuk_mcp-0.9.1.dist-info/RECORD
