Metadata-Version: 2.4
Name: chuk-mcp
Version: 0.9.1
Summary: Model Context Protocol client and server library with optional Pydantic support
Author-email: Chris Hay <chrishayuk@somejunkmailbox.com>
License: MIT
Project-URL: Homepage, https://github.com/chrishayuk/chuk-mcp
Project-URL: Repository, https://github.com/chrishayuk/chuk-mcp
Project-URL: Bug Tracker, https://github.com/chrishayuk/chuk-mcp/issues
Keywords: llm,openai,claude,mcp,client,protocol
Classifier: Development Status :: 4 - Beta
Classifier: Intended Audience :: Developers
Classifier: License :: OSI Approved :: MIT License
Classifier: Programming Language :: Python :: 3
Classifier: Programming Language :: Python :: 3.11
Classifier: Programming Language :: Python :: 3.12
Classifier: Programming Language :: Python :: 3.13
Classifier: Topic :: Software Development :: Libraries :: Python Modules
Classifier: Topic :: Communications
Classifier: Topic :: Scientific/Engineering :: Artificial Intelligence
Classifier: Framework :: AnyIO
Classifier: Typing :: Typed
Classifier: Operating System :: OS Independent
Classifier: Operating System :: POSIX :: Linux
Classifier: Operating System :: MacOS
Classifier: Operating System :: Microsoft :: Windows
Requires-Python: >=3.11
License-File: LICENSE
Requires-Dist: anyio>=4.9.0
Requires-Dist: httpx>=0.28.1
Requires-Dist: typing-extensions<5.0.0,>=4.7.1
Provides-Extra: pydantic
Requires-Dist: pydantic<3,>=2.11.1; extra == "pydantic"
Provides-Extra: http
Requires-Dist: httpx<1,>=0.28.1; extra == "http"
Provides-Extra: fast-json
Requires-Dist: orjson<4,>=3.10.0; extra == "fast-json"
Provides-Extra: full
Requires-Dist: pydantic<3,>=2.11.1; extra == "full"
Requires-Dist: httpx<1,>=0.28.1; extra == "full"
Requires-Dist: orjson<4,>=3.10.0; extra == "full"
Provides-Extra: dev
Requires-Dist: pydantic>=2.11.1; extra == "dev"
Requires-Dist: httpx>=0.28.1; extra == "dev"
Requires-Dist: orjson>=3.10.0; extra == "dev"
Requires-Dist: pytest>=8.3.5; extra == "dev"
Requires-Dist: pytest-asyncio>=0.26.0; extra == "dev"
Requires-Dist: pytest-cov>=6.0.0; extra == "dev"
Requires-Dist: coverage>=7.6.0; extra == "dev"
Requires-Dist: mypy>=1.14.1; extra == "dev"
Requires-Dist: ruff>=0.9.1; extra == "dev"
Requires-Dist: fastapi>=0.116.0; extra == "dev"
Requires-Dist: uvicorn>=0.35.0; extra == "dev"
Requires-Dist: pytz>=2025.2; extra == "dev"
Dynamic: license-file
